MANIFEST.in
README.md
setup.py
src/infi/__init__.py
src/infi.reboot.egg-info/PKG-INFO
src/infi.reboot.egg-info/SOURCES.txt
src/infi.reboot.egg-info/dependency_links.txt
src/infi.reboot.egg-info/entry_points.txt
src/infi.reboot.egg-info/namespace_packages.txt
src/infi.reboot.egg-info/not-zip-safe
src/infi.reboot.egg-info/requires.txt
src/infi.reboot.egg-info/top_level.txt
src/infi/reboot/__init__.py
src/infi/reboot/__version__.py
src/infi/reboot/_posix_uptime.c
src/infi/reboot/tests/__init__.py